ccrestoration/__init__.py
ccrestoration/arch/__init__.py
ccrestoration/arch/arch_util.py
ccrestoration/arch/basicvsr_arch.py
ccrestoration/arch/dat_arch.py
ccrestoration/arch/edsr_arch.py
ccrestoration/arch/edvr_arch.py
ccrestoration/arch/hat_arch.py
ccrestoration/arch/iconvsr_arch.py
ccrestoration/arch/msrswvsr_arch.py
ccrestoration/arch/rrdb_arch.py
ccrestoration/arch/scunet_arch.py
ccrestoration/arch/spynet_arch.py
ccrestoration/arch/srcnn_arch.py
ccrestoration/arch/srvgg_arch.py
ccrestoration/arch/swinir_arch.py
ccrestoration/arch/upcunet_arch.py
ccrestoration/auto/__init__.py
ccrestoration/auto/config.py
ccrestoration/auto/model.py
ccrestoration/cache_models/__init__.py
ccrestoration/config/__init__.py
ccrestoration/config/animesr_config.py
ccrestoration/config/basicvsr_config.py
ccrestoration/config/dat_config.py
ccrestoration/config/edsr_config.py
ccrestoration/config/edvr_config.py
ccrestoration/config/hat_config.py
ccrestoration/config/iconvsr_config.py
ccrestoration/config/realcugan_config.py
ccrestoration/config/realesrgan_config.py
ccrestoration/config/scunet_config.py
ccrestoration/config/spynet_config.py
ccrestoration/config/srcnn_config.py
ccrestoration/config/swinir_config.py
ccrestoration/model/__init__.py
ccrestoration/model/animesr_model.py
ccrestoration/model/auxiliary_base_model.py
ccrestoration/model/basicvsr_model.py
ccrestoration/model/dat_model.py
ccrestoration/model/edsr_model.py
ccrestoration/model/edvr_model.py
ccrestoration/model/hat_model.py
ccrestoration/model/iconvsr_model.py
ccrestoration/model/realcugan_model.py
ccrestoration/model/realesrgan_model.py
ccrestoration/model/scunet_model.py
ccrestoration/model/spynet_model.py
ccrestoration/model/sr_base_model.py
ccrestoration/model/srcnn_model.py
ccrestoration/model/swinir_model.py
ccrestoration/model/tile.py
ccrestoration/model/vsr_base_model.py
ccrestoration/type/__init__.py
ccrestoration/type/arch.py
ccrestoration/type/base_config.py
ccrestoration/type/base_model.py
ccrestoration-0.2.2.dist-info/LICENSE
ccrestoration-0.2.2.dist-info/METADATA
ccrestoration-0.2.2.dist-info/WHEEL
ccrestoration-0.2.2.dist-info/RECORD
